<title>第七話「友達」</title>

<div class="p-novel__body">

<div class="js-novel-text p-novel__text" style="line-height: 180%; font-size: 100%;">
<p id="L1">　俺は外に出てみることにした。</p>
<p id="L2">　せっかくロキシーが外に出るようにしてくれたのだ。</p>
<p id="L3">　無駄にはすまい。</p>
<p id="L4"><br></p>
<p id="L5">「父様。外で遊んできてもいいですか？」</p>
<p id="L6"><br></p>
<p id="L7">　ある日、植物辞典を片手にパウロにそう聞いてみた。</p>
<p id="L8">　この年頃の子供というものは、目を放すとすぐにどこかに行ってしまう。</p>
<p id="L9">　近所とはいえ、黙って出ては親も心配するだろうとの配慮だ。</p>
<p id="L10"><br></p>
<p id="L11">「外？　遊びに？　庭じゃなくてか？」</p>
<p id="L12">「はい」</p>
<p id="L13">「お、おお。もちろんだ」</p>
<p id="L14"><br></p>
<p id="L15">　あっさりと許可が出た。</p>
<p id="L16"><br></p>
<p id="L17">「思えば、お前には自由な時間を与えていなかったな。</p>
<p id="L18">　親の勝手で魔術と剣術を同時に習わせたが、子供には遊ぶことも必要だ」</p>
<p id="L19">「いい先生と巡り合わせて頂いて感謝しています」</p>
<p id="L20"><br></p>
<p id="L21">　厳格な教育パパだと思っていたが、わりと柔軟な思考をしているらしい。</p>
<p id="L22">　一日中剣術をしろと言われる可能性まで考慮していたのだが、</p>
<p id="L23">　拍子抜けだ。</p>
<p id="L24">　感覚派だが、根性論は持っていないらしい。</p>
<p id="L25"><br></p>
<p id="L26">「それにしても、お前が外に、か。</p>
<p id="L27">　身体の弱い子だと思っていたが、時が経つのはあっという間だな」</p>
<p id="L28">「身体が弱いなんて思ってたんですか？」</p>
<p id="L29"><br></p>
<p id="L30">　初耳だ。</p>
<p id="L31">　病気なんてしたことないのに……。</p>
<p id="L32"><br></p>
<p id="L33">「全然泣かなかったからな」</p>
<p id="L34">「そうですか。まぁ、今が大丈夫ならいいじゃないですか。</p>
<p id="L35">　丈夫で愛嬌のある息子に育っていますよ。びろーん」</p>
<p id="L36"><br></p>
<p id="L37">　と、ほっぺたを引っ張って変顔をしてみせると、パウロは苦笑した。</p>
<p id="L38"><br></p>
<p id="L39">「そういう、子供らしくない所が逆に心配なんだがな」</p>
<p id="L40">「長男がしっかりしている事の何が不満なんですか」</p>
<p id="L41">「いや、不満は無いんだが」</p>
<p id="L42">「不満たらたらの顔で、もっとグレイラット家の跡継ぎとして相応しい人間になれ、とか言ってもいいんですよ？」</p>
<p id="L43">「自慢じゃないが、父さんがお前ぐらいの頃は女の子のスカートをめくる事に夢中な悪ガキだった」</p>
<p id="L44">「スカートめくりですか」</p>
<p id="L45"><br></p>
<p id="L46">　この世界にもあるのか。</p>
<p id="L47">　しかし自分で悪ガキつったな、この男。</p>
<p id="L48"><br></p>
<p id="L49">「グレイラット家に相応しい人間になりたいなら、ガールフレンドの一人でも連れてきなさい」</p>
<p id="L50"><br></p>
<p id="L51">　なに？　ウチってそういう家柄なの？</p>
<p id="L52">　辺境を守る騎士で下級貴族って話じゃなかったの？</p>
<p id="L53">　格式とか無いの？　いや、所詮は下級。そんなもんか。</p>
<p id="L54"><br></p>
<p id="L55">「わかりました。では、めくるスカートを見つけに村に行ってまいります」</p>
<p id="L56">「あ、女の子には優しくするんだぞ。</p>
<p id="L57">　それに、自分の方が力が強くて魔術が使えるからっていばっちゃだめだ。</p>
<p id="L58">　男の強さは威張るためにあるんじゃないからな」</p>
<p id="L59"><br></p>
<p id="L60">　お、今いいこと言った。</p>
<p id="L61">　いいねいいね、生前のうちの兄弟にも聞かせてやりたいよ。</p>
<p id="L62">　そうだな、力ってのはただ振るっても意味がない。</p>
<p id="L63">　パウロの言うことはもっともだよ。</p>
<p id="L64">　俺も理解者さ。</p>
<p id="L65"><br></p>
<p id="L66">「わかっていますよ父様。</p>
<p id="L67">　強さとは、女の子にいい格好を見せる時のためにあるんですよね」</p>
<p id="L68">「……いや、そうじゃなくてな」</p>
<p id="L69"><br></p>
<p id="L70">　あれ？</p>
<p id="L71">　そういう話の流れじゃなかったのか？</p>
<p id="L72">　失敗失敗。てへぺろ。</p>
<p id="L73"><br></p>
<p id="L74">「冗談です。弱い者を守るためにあるんですよね？」</p>
<p id="L75">「うむ、そのとおりだ」</p>
<p id="L76"><br></p>
<p id="L77">　そんな会話の後、植物辞典を小脇に抱え、ロキシーにもらった杖を腰に差し、</p>
<p id="L78">　さぁ出かけようかと思った所で、ふと気づいて俺は振り返った。</p>
<p id="L79"><br></p>
<p id="L80">「ああそうだ、父様。</p>
<p id="L81">　これからもちょくちょく外出すると思いますが、出かける時は必ず家の誰かに言いますし、剣術と魔術の鍛錬は毎日欠かさずやります。日が落ちて暗くなる前には帰りますし、危ない所には近づきません」</p>
<p id="L82">「あ………ああ」</p>
<p id="L83"><br></p>
<p id="L84">　念のため、そう言い残しておく。</p>
<p id="L85">　パウロはなぜか唖然としていた。</p>
<p id="L86">　本当なら、お前が言わなきゃいけない事だぜ？</p>
<p id="L87"><br></p>
<p id="L88">「では、行って来ます」</p>
<p id="L89">「……………行ってらっしゃい」</p>
<p id="L90"><br></p>
<p id="L91">　こうして、俺は家を出た。</p>
<p id="L92"><br></p>
<p id="L93"><br></p>
<p id="L94">---</p>
<p id="L95"><br></p>
<p id="L96"><br></p>
<p id="L97">　数日が経過した。</p>
<p id="L98"><br></p>
<p id="L99">　外は怖くない。順調だ。</p>
<p id="L100">　すれ違う人と爽やかな挨拶をかわせるようにまでなった。</p>
<p id="L101">　人々は俺のことを知っていた。</p>
<p id="L102">　パウロとゼニスの子供、ロキシーの弟子として。</p>
<p id="L103">　初対面の相手には挨拶と自己紹介。</p>
<p id="L104">　二度目の人にはこんにちわ。</p>
<p id="L105"><br></p>
<p id="L106">　誰もがにこやかな顔で挨拶を返してくれる。</p>
<p id="L107">　こんな晴れやかな気分は久しぶりだ。</p>
<p id="L108">　半分以上がパウロとロキシーの知名度のおかげ。</p>
<p id="L109">　残りは全てロキシーのおかげだ。</p>
<p id="L110"><br></p>
<p id="L111">　<ruby>御神体<rp>(</rp><rt>パンツ</rt><rp>)</rp></ruby>を大切にしよう。　</p>
<p id="L112"><br></p>
<p id="L113"><br></p>
<p id="L114">---</p>
<p id="L115"><br></p>
<p id="L116"><br></p>
<p id="L117">　さて。</p>
<p id="L118">　外に出た主な目的は、主に自分の足で歩き、地理を覚えることだ。</p>
<p id="L119">　地理さえ覚えておけば、突然家から叩きだされても、迷ったりしないからな。</p>
<p id="L120"><br></p>
<p id="L121">　同時に、植物系の調査も行いたい。</p>
<p id="L122">　ちょうど植物辞典もあることだし、食べられるもの、食べられないもの、薬になるもの、毒になるもの……。</p>
<p id="L123">　それぞれ見分けられるようにしておいた方がいい。</p>
<p id="L124">　そうすれば、突然家から叩きだされても、飯に困ることはないからな。</p>
<p id="L125"><br></p>
<p id="L126">　ロキシーは触りしか教えてくれなかったが、この村では麦と野菜と香水の材料を栽培しているらしい。</p>
<p id="L127">　香水の材料、バティルスの花というのはラベンダーによく似た植物だ。</p>
<p id="L128">　薄紫色をしており、食べることもできるのだとか。</p>
<p id="L129">　そういった目立つものを中心に、俺は目についた植物を片っ端から植物辞典で照合していった。</p>
<p id="L130"><br></p>
<p id="L131"><br></p>
<p id="L132">　といっても、村はそれほど広く無いし、大した植物があるわけじゃない。</p>
<p id="L133">　何日もしないうちに、俺の行動半径は広がり、森の方へと向くようになっていた。</p>
<p id="L134">　森には植物が多いからだ。</p>
<p id="L135"><br></p>
<p id="L136">「確か、森は魔力溜りができやすいから、危ないんだったな」</p>
<p id="L137"><br></p>
<p id="L138">　魔力溜まりが出来やすい環境は、魔物の発生率が高い。</p>
<p id="L139">　魔力による突然変異で生まれてくるのが魔物だからな。</p>
<p id="L140">　なぜ森に魔力溜まりが出来やすいのかは知らんが。</p>
<p id="L141"><br></p>
<p id="L142">　もっとも、このあたりはそもそも魔物が出にくい上、</p>
<p id="L143">　定期的に魔物狩りを行なわれているので比較的安全だ。</p>
<p id="L144"><br></p>
<p id="L145">　魔物狩りとは文字通り。</p>
<p id="L146">　月に一度、騎士、狩人、自警団たちといった男衆が、</p>
<p id="L147">　総出で森に入って魔物を一掃するらしい。</p>
<p id="L148"><br></p>
<p id="L149">　とはいえ、森の奥で凶悪な魔物がいきなり出現することもあるらしい。</p>
<p id="L150"><br></p>
<p id="L151">　俺は魔術を憶えて多少は戦える力は手に入れたかもしれない。</p>
<p id="L152">　だが、元は喧嘩もロクにしたことのない引きこもりだ。</p>
<p id="L153">　増長してはいけない。</p>
<p id="L154">　実戦経験も無いし、調子に乗ってヘマしたら目も当てられない。</p>
<p id="L155">　そうして死んでいった奴を何人も見てきた……漫画でな。</p>
<p id="L156"><br></p>
<p id="L157">　そもそも、俺は血の気の多い方じゃない。</p>
<p id="L158">　戦いは極力避けるのが一番だと思っている。</p>
<p id="L159"><br></p>
<p id="L160">　魔物に遭遇したら逃げ帰ってパウロに報告しよう。</p>
<p id="L161">　そうしよう。</p>
<p id="L162"><br></p>
<p id="L163"><br></p>
<p id="L164">　そんな事を考えつつ、俺は小高い丘を上っていた。</p>
<p id="L165">　丘の上には、大きな木が一本だけ立っている。</p>
<p id="L166">　この辺りで一番大きな木だ。</p>
<p id="L167"><br></p>
<p id="L168">　自分で歩いた村の地理を確かめるのには高い所がいい。</p>
<p id="L169">　ついでに、このへんで一番大きなあの木が何の木なのかを確かめるつもりだった。</p>
<p id="L170"><br></p>
<p id="L171">　と、その時。</p>
<p id="L172"><br></p>
<p id="L173">「魔族は村にはいんなよなー！」</p>
<p id="L174"><br></p>
<p id="L175">　風にのってそんな声が聞こえてきた。</p>
<p id="L176">　この声音で、嫌な記憶が蘇った。</p>
<p id="L177"><br></p>
<p id="L178">　引きこもりの原因となった高校生活。</p>
<p id="L179">　ホーケーと仇名された頃の悪夢。</p>
<p id="L180">　丁度、俺の仇名を呼ぶ時の声音と今の声音が似ていた。</p>
<p id="L181">　あからさまに格下の相手を数で虐げる時の声音だ。</p>
<p id="L182"><br></p>
<p id="L183">「あっちいけよなー！」</p>
<p id="L184">「くらえー！」</p>
<p id="L185">「よっしゃめいちゅーぅ！」</p>
<p id="L186"><br></p>
<p id="L187">　見れば、そこには先日の雨で泥沼みたいになっている畑。</p>
<p id="L188">　その中で体中泥だらけにしている三人の子供たちが、</p>
<p id="L189">　道を歩いている一人の少年に向かって泥を投げつけていた。</p>
<p id="L190"><br></p>
<p id="L191">「頭に当てたら１０点な！」</p>
<p id="L192">「っしゃー！」</p>
<p id="L193">「俺あたった！　あたったって！」</p>
<p id="L194"><br></p>
<p id="L195">　うわー。</p>
<p id="L196">　いやだいやだ。</p>
<p id="L197">　イジメの現場だ。</p>
<p id="L198">　ああいう奴らは、相手が格下なら何をやってもいいと思ってるんだ。</p>
<p id="L199">　エアガンを買ったら、そいつに向けて撃ってもいいと考えているんだ。</p>
<p id="L200">　人に向けて撃つなと書いてあるのにだ。</p>
<p id="L201">　相手を人として見てないからだ。</p>
<p id="L202">　人として許せんね。</p>
<p id="L203"><br></p>
<p id="L204">　少年はというと、足早にそこを去ればいいのに、なぜか遅々として進んで行かない。</p>
<p id="L205">　よく見ると、</p>
<p id="L206">　バスケットのようなものを胸元に抱えており、</p>
<p id="L207">　それに泥玉が当たらないように身を縮こまらせているからだ。</p>
<p id="L208">　そのため、イジメっ子たちの攻撃から逃げ切れないでいた。</p>
<p id="L209"><br></p>
<p id="L210">「なんか持ってるぜ！」</p>
<p id="L211">「魔族の宝か！」</p>
<p id="L212">「どこで盗んできたんだー！」</p>
<p id="L213">「あれにぶつけたら１００点な！」</p>
<p id="L214">「宝を奪いとろうぜ！」</p>
<p id="L215"><br></p>
<p id="L216">　俺は少年の方に向かって走っていく。</p>
<p id="L217">　走りながら、魔術で泥玉を作る。</p>
<p id="L218">　そして射程距離に入った瞬間、全力投球。</p>
<p id="L219"><br></p>
<p id="L220">「わっぶ」</p>
<p id="L221">「なんだ！？」</p>
<p id="L222"><br></p>
<p id="L223">　リーダー格っぽい、一際体の大きい奴の顔面に命中。</p>
<p id="L224"><br></p>
<p id="L225">「ってぇ、目に入った」</p>
<p id="L226">「なんだよお前！」</p>
<p id="L227">「関係ねーやつが入ってくんなよ！」</p>
<p id="L228">「魔族の味方すんのかよ！」</p>
<p id="L229"><br></p>
<p id="L230">　標的が一瞬で俺の方に向いた。</p>
<p id="L231">　こういうのはどこの世界でも一緒だな。</p>
<p id="L232"><br></p>
<p id="L233">「魔族の味方じゃありません。弱い者の味方なんです」</p>
<p id="L234"><br></p>
<p id="L235">　どや顔で言った。</p>
<p id="L236">　が、少年たちは自分たちこそが正義という顔で、俺を糾弾した。</p>
<p id="L237"><br></p>
<p id="L238">「かっこつけてんじゃねえよ！」</p>
<p id="L239">「おまえ、騎士んところのヤツだな！」</p>
<p id="L240">「お坊ちゃんかよ！」</p>
<p id="L241"><br></p>
<p id="L242">　あらやだ。身元がバレてーら。</p>
<p id="L243"><br></p>
<p id="L244">「いーのかー！　騎士の子供がこんな事して！」</p>
<p id="L245">「騎士が魔族の味方だって言ってやろー！」</p>
<p id="L246">「てか、兄ちゃんたち呼んでこようぜ！」</p>
<p id="L247">「兄ちゃーん！　変なのがいるぅー！」</p>
<p id="L248"><br></p>
<p id="L249">　子供たちは仲間を呼んだ！</p>
<p id="L250">　しかし誰も現れなかった。</p>
<p id="L251">　しかし、俺の足はすくんだ！</p>
<p id="L252"><br></p>
<p id="L253">　ぐ、三人もいるとはいえ、子供に叫ばれて足が竦むとは……。</p>
<p id="L254">　情けない。</p>
<p id="L255">　これがイジメられて引きこもった者のサガか……。</p>
<p id="L256"><br></p>
<p id="L257">「う、うるさい！　三人で寄ってたかって一人を攻撃するとかお前ら最低だ！」</p>
<p id="L258"><br></p>
<p id="L259">　はぁ？　って顔された。</p>
<p id="L260">　む、むかつく。</p>
<p id="L261"><br></p>
<p id="L262">「てめぇこそ大声だしてんじゃねえよ、バァーカ！」</p>
<p id="L263"><br></p>
<p id="L264">　むかついたので、泥玉をもう一発投げる。</p>
<p id="L265">　はずれた。</p>
<p id="L266"><br></p>
<p id="L267">「てめっ！」</p>
<p id="L268">「あいつどこに泥もってんだよ！」</p>
<p id="L269">「いいからやり返せ！」</p>
<p id="L270"><br></p>
<p id="L271">　３倍になって返ってきた。</p>
<p id="L272">　パウロに教えてもらった足捌きと魔術を駆使して華麗に回避。</p>
<p id="L273"><br></p>
<p id="L274">「あ、あたんねぇ！」</p>
<p id="L275">「よけんじゃねえよ！」</p>
<p id="L276"><br></p>
<p id="L277">　ふはは、当たらなければどうという事はない！</p>
<p id="L278"><br></p>
<p id="L279">　しばらく三人は泥玉を投げ続けていたが、俺に当たらないとわかると、</p>
<p id="L280">　急につまんなくなったとでも言わんばかりに、手を止めた。</p>
<p id="L281"><br></p>
<p id="L282">「あーあ！　つまんねぇの！」</p>
<p id="L283">「もう行こうぜ！」</p>
<p id="L284">「騎士んとこのが魔族と仲良くしてたって言いふらそーぜ！」</p>
<p id="L285"><br></p>
<p id="L286">　別に俺ら負けてないから。</p>
<p id="L287">　飽きたからやめただけだから。</p>
<p id="L288">　そんな口調で言い残して、三人のクソガキは畑の向こうへと去っていった。</p>
<p id="L289"><br></p>
<p id="L290">　やった！　生まれて初めてイジメっ子を倒したぞ！</p>
<p id="L291">　じ、自慢にはならねえな。</p>
<p id="L292"><br></p>
<p id="L293">　ふぅ。</p>
<p id="L294">　それにしても、やっぱ喧嘩は得意になれないな。</p>
<p id="L295">　殴り合いにならなくてよかった。</p>
<p id="L296"><br></p>
<p id="L297">「君、大丈夫？　荷物は無事？」</p>
<p id="L298"><br></p>
<p id="L299">　とりあえず、泥を投げつけられていた少年に振り返ってみると……。</p>
<p id="L300"><br></p>
<p id="L301">　わーぉ……。</p>
<p id="L302">　まぁびっくり。</p>
<p id="L303">　驚くほどの美少年。</p>
<p id="L304">　同じぐらいの歳とは思えない。</p>
<p id="L305"><br></p>
<p id="L306">　くそう、パウロがもっと美男子系だったら俺も……。</p>
<p id="L307"><br></p>
<p id="L308">　いや、パウロは悪くない。ゼニスも優秀だ。</p>
<p id="L309">　だからこの顔は大丈夫だ。</p>
<p id="L310">　生前のあのニキビと皮下脂肪だらけの顔に比べれば大丈夫だ。</p>
<p id="L311">　十分いけるって、うん。</p>
<p id="L312"><br></p>
<p id="L313">「う……うん……だ、大丈夫……」</p>
<p id="L314"><br></p>
<p id="L315">　少年は怯えた顔を向けてきた。</p>
<p id="L316">　まるで小動物のような保護欲を誘う。</p>
<p id="L317">　ショタコンのお姉さんがいたら、一発でジュンってなるだろう。</p>
<p id="L318"><br></p>
<p id="L319">　が、今はそれもこびりついた泥のせいで台無しだ。</p>
<p id="L320">　服は泥だらけ。顔の半分に泥が付着し、頭にいたっては泥一色。</p>
<p id="L321">　バスケットを守れたのは奇跡的といってもいい。</p>
<p id="L322">　しょうがないな。</p>
<p id="L323"><br></p>
<p id="L324">「ちょっと、そこに荷物置いて、そっちの用水路の前でひざまずいて」</p>
<p id="L325">「え……？　え……？」</p>
<p id="L326"><br></p>
<p id="L327">　少年は目を白黒させながらも、なぜか言われたままにしてくれる。</p>
<p id="L328">　あまり人の言うことに逆らわない子らしい。</p>
<p id="L329">　まあ、逆らう子ならさっきのイジメにも反撃してるか。</p>
<p id="L330"><br></p>
<p id="L331">　少年は四つん這いで用水路を覗きこむような姿勢になっている。</p>
<p id="L332">　ショタコンのお兄さんがいたら、一発でズグンってなるだろう。</p>
<p id="L333"><br></p>
<p id="L334">「目をつぶってろ」</p>
<p id="L335"><br></p>
<p id="L336">　俺は水を火の魔術で適当に調整する。</p>
<p id="L337">　熱すぎず冷たすぎず、四十度ほどのお湯を作りだす。</p>
<p id="L338">　そいつを少年の頭にぶっかける。</p>
<p id="L339"><br></p>
<p id="L340">「わぁっ！」</p>
<p id="L341"><br></p>
<p id="L342">　慌てて逃げようとする少年の首根っこを掴んで、泥を綺麗に洗い落とす。</p>
<p id="L343">　最初は暴れていたけど、お湯の温度になれてくると、またおとなしくなった。</p>
<p id="L344">　服のほうは……家で洗濯したほうがいいだろう。</p>
<p id="L345"><br></p>
<p id="L346">「よし、こんなもんかな」</p>
<p id="L347"><br></p>
<p id="L348">　泥が落ちたので、俺は風を火の魔術で適当に調整してドライヤーのように温風を送りつつ、ハンカチで少年の顔を丁寧に拭ってやった。</p>
<p id="L349"><br></p>
<p id="L350">　すると、エルフのようにとんがった耳と、</p>
<p id="L351">　日光に輝く、綺麗なエメラルドグリーンの髪が現れたのだ。</p>
<p id="L352"><br></p>
<p id="L353">　その色を見た瞬間、ロキシーの言葉が思い出される。</p>
<p id="L354"><br></p>
<p id="L355">『エメラルドグリーンの髪をもつ種族には、絶対に近寄ってはいけません』</p>
<p id="L356"><br></p>
<p id="L357">　ん？</p>
<p id="L358">　いや、ちょっと違ったな。</p>
<p id="L359">　確か……</p>
<p id="L360"><br></p>
<p id="L361">『エメラルドグリーンの髪を持っていて、</p>
<p id="L362">　額に赤い宝石のようなのがついた種族には、絶対に近づかないでください』</p>
<p id="L363"><br></p>
<p id="L364">　そうだ。確かこうだ。</p>
<p id="L365">　額に赤い宝石のようなのがついた種族、だ。</p>
<p id="L366">　少年の額はというと、白い綺麗なおでこちゃん。</p>
<p id="L367">　オッケー、セーフ。</p>
<p id="L368">　彼は危ないスペルド族ではない。</p>
<p id="L369"><br></p>
<p id="L370">「あ、ありがとう……」</p>
<p id="L371"><br></p>
<p id="L372">　お礼を言われて、ハッと我に返った。</p>
<p id="L373">　おうおう、ビビらせてくれやがって。</p>
<p id="L374">　腹いせにちょっとばかし、偉そうにアドバイスを開始する。</p>
<p id="L375"><br></p>
<p id="L376">「君ね。ああいう奴らはちゃんとやり返さないと付け上がるよ」</p>
<p id="L377">「勝てないよ……」</p>
<p id="L378">「抵抗する意思が大事なんだ」</p>
<p id="L379">「だって、いつもはもっとおっきな子もいるんだもん……。</p>
<p id="L380">　痛いのは嫌だよ……」</p>
<p id="L381"><br></p>
<p id="L382">　なるほど。</p>
<p id="L383">　抵抗すると仲間を呼んで徹底的に痛めつけるわけか。</p>
<p id="L384">　こういうのはどこの世界も一緒だな。</p>
<p id="L385">　ロキシーが頑張ったから大人の方は魔族を受け入れるようになったみたいだけど、子供の方はそうは行かないか。</p>
<p id="L386">　子供ってやつは残酷だ。</p>
<p id="L387">　ちょっと違うだけで爪弾きにしやがる。</p>
<p id="L388"><br></p>
<p id="L389">「君も大変だね。髪の色がスペルド族に似てるってだけでイジメられて」</p>
<p id="L390">「き、きみは、平気……なの？」</p>
<p id="L391">「先生が魔族だったからね。君はなんていう種族なの？」</p>
<p id="L392"><br></p>
<p id="L393">　ロキシーのミグルド族はスペルド族と近しいと言っていた。</p>
<p id="L394">　もしかすると、彼もそんな種族なのかもしれない。</p>
<p id="L395">　そう思って聞いたのだが、少年は首を振った。</p>
<p id="L396"><br></p>
<p id="L397">「………わかんない」</p>
<p id="L398"><br></p>
<p id="L399">　この歳なら、そういうもんなのかな？</p>
<p id="L400"><br></p>
<p id="L401">「お父さんの種族は？」</p>
<p id="L402">「……半分だけ長耳族。もう半分は人間だって」</p>
<p id="L403">「お母さんは？」</p>
<p id="L404">「人間だけど、ちょっとだけ獣人族が混じってるって……」</p>
<p id="L405"><br></p>
<p id="L406">　<ruby>半長耳族<rp>(</rp><rt>ハーフエルフ</rt><rp>)</rp></ruby>と、クォーターの獣人？</p>
<p id="L407">　それでこんな髪になるのか……？</p>
<p id="L408">　と思っていたら、少年は両目に涙を浮かべていた。</p>
<p id="L409"><br></p>
<p id="L410">「……だから、魔族じゃないって……お父さん、いうけど……。</p>
<p id="L411">　………髪の色、お父さんとも、お母さんとも、違う……」</p>
<p id="L412"><br></p>
<p id="L413">　めそめそと泣き出す少年の頭をよしよしと撫でておく。</p>
<p id="L414"><br></p>
<p id="L415">　しかし、髪の色が違うとは大問題だな。</p>
<p id="L416">　お母さんが浮気していた可能性が出てくる。</p>
<p id="L417"><br></p>
<p id="L418">「違うのは髪の色だけ？」</p>
<p id="L419">「……耳も、お父さんより長い……」</p>
<p id="L420">「そっか……」</p>
<p id="L421"><br></p>
<p id="L422">　耳が長くて髪が緑の魔族……どこかにはいそうだな。</p>
<p id="L423">　うーん、他人の家庭の事情にまではあんまり踏み入りたくない。</p>
<p id="L424">　けど、俺もかつてはイジメられっ子だった。</p>
<p id="L425">　どうにかしてやりたい。</p>
<p id="L426">　ちょっと髪の色が緑色ってだけでイジメられるのは可哀想だ。</p>
<p id="L427">　俺の遭っていたイジメは身から出た錆の部分もある。</p>
<p id="L428">　時間が巻き戻ってあの瞬間に戻れば、次はもっとうまくやれる自信がある。</p>
<p id="L429">　けど、少年は違うだろう。</p>
<p id="L430">　生まれを変えるのは、自分の努力では不可能だ。</p>
<p id="L431">　生まれた時から、髪の色がちょっと緑色だっただけで道端で泥玉を投げつけられる……。</p>
<p id="L432">　うう……考えるだけで尿が出そうだ。</p>
<p id="L433"><br></p>
<p id="L434">「お父さんは優しくしてくれてる？」</p>
<p id="L435">「……うん。怒ると怖いけど、ちゃんとしてれば怒られない」</p>
<p id="L436">「そっか。お母さんは？」</p>
<p id="L437">「優しい」</p>
<p id="L438"><br></p>
<p id="L439">　ふむ。</p>
<p id="L440">　声音から察するに、父親も母親もきちんと愛情を注いでいるようだ。</p>
<p id="L441">　浮気ではなく、本当の子供のように……。</p>
<p id="L442">　いや、実際に見てみなければわからないか。</p>
<p id="L443"><br></p>
<p id="L444">「よし、じゃあ行こうか」</p>
<p id="L445">「………ど、どこに？」</p>
<p id="L446">「君についていくよ」</p>
<p id="L447"><br></p>
<p id="L448">　子供についていけば親が現れる。</p>
<p id="L449">　自然の摂理だ。</p>
<p id="L450"><br></p>
<p id="L451">「…………な、なんで、ついてくるの？」</p>
<p id="L452">「いや……、さっきの奴らが戻ってくるかもしれないし。送るよ。</p>
<p id="L453">　家に帰るの？　それとも、それをどこかに届けに？」</p>
<p id="L454">「お弁当……お父さんに、届けに……」</p>
<p id="L455"><br></p>
<p id="L456">　お父さんはハーフエルフだったか。</p>
<p id="L457"><br></p>
<p id="L458">　物語に出てくるエルフといえば、長寿で閉鎖的な暮らしをしていて、傲慢な性格で他の種族を見下している。</p>
<p id="L459">　弓と魔法が得意で、水と風の魔法を得意とする。</p>
<p id="L460">　あとは名前の通り耳が長いことぐらいだ。</p>
<p id="L461">　そんな種族だ。</p>
<p id="L462"><br></p>
<p id="L463">　ロキシーの話によると、</p>
<p id="L464">　「大体それで合ってるが、別に閉鎖的ではない」らしい。</p>
<p id="L465"><br></p>
<p id="L466">　やっぱこの世界のエルフも美男美女が多いのだろうか。</p>
<p id="L467">　いや、エルフに美男美女が多いというのは日本人の勝手な思い込みだ。</p>
<p id="L468">　洋ゲーに出てくるエルフは過度にトンがった顔をしててとても美男美女には見えなかった。</p>
<p id="L469">　大体、日本人のオタクと外国人のパンピーが同じ尺度であるはずがない。</p>
<p id="L470"><br></p>
<p id="L471">　もっとも、この少年の両親は美男美女のコンビで確定っぽいが。</p>
<p id="L472"><br></p>
<p id="L473">「あの………なんで、守って、くれたの？」</p>
<p id="L474"><br></p>
<p id="L475">　少年は保護欲をかきたてる仕草で、おずおずと聞いてくる。</p>
<p id="L476"><br></p>
<p id="L477">「弱い者の味方をしろと父様に言われてるんだ」</p>
<p id="L478">「でも……他の子に、仲間はずれにされるかも……」</p>
<p id="L479"><br></p>
<p id="L480">　そうだろうとも。</p>
<p id="L481">　イジメられっこを助けたらイジメられました。</p>
<p id="L482">　なんてのは、よくある話だ。</p>
<p id="L483"><br></p>
<p id="L484">「その時は君が遊んでくれよ。今日から友達さ」</p>
<p id="L485">「えっ！？」</p>
<p id="L486"><br></p>
<p id="L487">　だから、二人で徒党を組むのだ。</p>
<p id="L488">　イジメの連鎖は、助けられた方が裏切ることで起きる。</p>
<p id="L489">　助けられた方が責任を持って、助けてくれた恩を返すのだ。</p>
<p id="L490">　まあ、少年の場合はイジメの原因がもっと根の深い部分にあるので、</p>
<p id="L491">　裏切ってイジメっこの側になるとは思わないが。</p>
<p id="L492"><br></p>
<p id="L493">「あ、家の手伝いとか忙しい？」</p>
<p id="L494">「う、ううん」</p>
<p id="L495"><br></p>
<p id="L496">　向こうの都合も聞いていなかったなと思ったが、ぶんぶんと首を振られた。</p>
<p id="L497">　いいね。その表情。</p>
<p id="L498">　ショタコンのお姉さんがいたら一発でホイホイ釣れるだろう。</p>
<p id="L499"><br></p>
<p id="L500">　ふむ。</p>
<p id="L501">　これはいいかもしれない。</p>
<p id="L502"><br></p>
<p id="L503">　この顔なら、将来的に女の子にモテモテになるだろう。</p>
<p id="L504">　そして、つるんでいれば、そのおこぼれが俺の方にくるかもしれない。</p>
<p id="L505">　俺の顔は大したレベルじゃないけど、男二人が並んでいた時、片方のレベルが高ければもう片方もそれなりに見えるものなのだ。</p>
<p id="L506">　ちょっと自分に自信がない子は、きっと俺を狙うはず。</p>
<p id="L507">　自信満々でぐいぐい来られるより、ちょっと自信なさそうな子の方が俺の好みだ。</p>
<p id="L508"><br></p>
<p id="L509">　いける。</p>
<p id="L510">　美少女が自分の近くにブスを置いて引き立て役にする。</p>
<p id="L511">　その逆をやるのだ。</p>
<p id="L512">　いける。</p>
<p id="L513"><br></p>
<p id="L514">「そういや、名前を聞いてなかったな。俺はルーデウス」</p>
<p id="L515">「シル…フ…―――」</p>
<p id="L516"><br></p>
<p id="L517">　小声でぼそぼそというので後半がやや聞き取りにくかったが、シルフか。</p>
<p id="L518"><br></p>
<p id="L519">「いい名前じゃないか。まるで風の精霊のようだ」</p>
<p id="L520"><br></p>
<p id="L521">　そう言うと、シルフは顔を赤くして「うん」と頷いた。</p>
<p id="L522"><br></p>
<p id="L523"><br></p>
<p id="L524">---</p>
<p id="L525"><br></p>
<p id="L526"><br></p>
<p id="L527">　シルフの父親ロールズは美形だった。</p>
<p id="L528">　尖った耳に、輝くような金髪、線は細いが筋肉が無いわけではない。</p>
<p id="L529">　ハーフエルフの名に恥じぬ、エルフと人間のいい所取りをしたような男性だった。</p>
<p id="L530">　彼は森の脇にある櫓で、弓を片手に森を監視していた。</p>
<p id="L531"><br></p>
<p id="L532">「お父さん、これ、お弁当……」</p>
<p id="L533">「お、いつもすまないなルフィ。今日はイジメられなかったかい？」</p>
<p id="L534">「大丈夫、助けてもらった」</p>
<p id="L535"><br></p>
<p id="L536">　目線で紹介されて、俺は軽く会釈をする。</p>
<p id="L537">　ルフィというのは愛称か。</p>
<p id="L538">　手とかが伸びそうな感じである。</p>
<p id="L539">　シルフもあれぐらい脳天気で傍若無人ならイジメられたりしなかったろうに。</p>
<p id="L540"><br></p>
<p id="L541">「初めまして。ルーデウス・グレイラットです」</p>
<p id="L542">「グレイラット……もしかして、パウロさんの所の？」</p>
<p id="L543">「はい。パウロは父です」</p>
<p id="L544">「おお、話には聞いていたが、礼儀正しい子だ。</p>
<p id="L545">　おっと、申し遅れた。ロールズです。普段は森で狩りをしています」</p>
<p id="L546"><br></p>
<p id="L547">　聞く所によると、ここは見たまんま森から魔物が出てこないように見張る櫓で、</p>
<p id="L548">　村の男衆が持ち回りで見張りをしているらしい。24時間体制で。</p>
<p id="L549">　当然ながらパウロにも当番があり、ロールズはそこでパウロと知り合い、互いに生まれた子供の事であれこれと相談しあったのだとか。</p>
<p id="L550"><br></p>
<p id="L551">「ウチの子はこんな見た目だが、ちょっと先祖返りをしてしまっただけなんだ。</p>
<p id="L552">　仲良くしてやってほしい」</p>
<p id="L553">「もちろんです。仮にシルフがスペルド族だったとしても、僕は態度を変えたりはしませんよ。</p>
<p id="L554">　父様の名誉に掛けてもね」</p>
<p id="L555"><br></p>
<p id="L556">　そう言うと、ロールズは感嘆の声を上げた。</p>
<p id="L557"><br></p>
<p id="L558">「その歳で名誉かぁ……優秀な子でパウロさんがうらやましいなぁ」</p>
<p id="L559">「小さい頃に優秀だった子供が、大人になっても優秀とは限りません。</p>
<p id="L560">　羨ましく思うのは、シルフが大人になってからでも遅くはありませんよ」</p>
<p id="L561"><br></p>
<p id="L562">　シルフのフォローを入れておいてやる。</p>
<p id="L563"><br></p>
<p id="L564">「なるほど……パウロさんの言っていた通りだ」</p>
<p id="L565">「……父はなんと？」</p>
<p id="L566">「君と話していると親として自信を失うらしい」</p>
<p id="L567">「そうですか。では、これからはもう少し悪さをして説教をさせてあげることにしますかね」</p>
<p id="L568"><br></p>
<p id="L569">　などと話していると、服の裾を引っ張られた。</p>
<p id="L570">　見れば、シルフがうつむきながら俺の裾を引いていた。</p>
<p id="L571">　大人同士の話は子供にはつまらんか。　</p>
<p id="L572"><br></p>
<p id="L573">「ロールズさん。ちょっと二人で遊んできてもいいですか？」</p>
<p id="L574">「ああ、もちろんだとも。ただし、森の方には近づかないように」</p>
<p id="L575"><br></p>
<p id="L576">　それは言われるまでもないが……。</p>
<p id="L577">　ちょっと足りないんじゃないかね？</p>
<p id="L578"><br></p>
<p id="L579">「ここに来る途中に大樹のある丘がありましたので、あの辺りで遊んでいると思います。</p>
<p id="L580">　暗くなる前に責任を持ってシルフを送り帰します。帰りに丘の方を見て、家に帰ってもいなければ、</p>
<p id="L581">　なんらかの事件に巻き込まれた可能性が高いので、捜索をお願いします」</p>
<p id="L582">「あ……ああ」</p>
<p id="L583"><br></p>
<p id="L584">　なにせ、携帯電話もない世界だ。</p>
<p id="L585">　ほうれんそうはキッチリ守るのが大事だ。</p>
<p id="L586">　トラブルを全て避ける事は出来ない。</p>
<p id="L587">　すぐにリカバリーするのが大切なのだ。</p>
<p id="L588">　この国はかなり治安がいいみたいだが、どこに危険が潜んでいるかわかったもんじゃない。</p>
<p id="L589"><br></p>
<p id="L590">　唖然としているロールズを尻目に、俺達は丘の木へと戻った。</p>
<p id="L591"><br></p>
<p id="L592"><br></p>
<p id="L593"><br></p>
<p id="L594">「さて、何をして遊ぼうか」</p>
<p id="L595">「わかんない……と、友達と、遊んだことないから……」</p>
<p id="L596"><br></p>
<p id="L597">　友達、という部分でちょっと躊躇った。</p>
<p id="L598">　きっと、今まで友達がいなかったのだろう。</p>
<p id="L599">　可哀想に……。</p>
<p id="L600">　いや、俺もいなかったけどな。</p>
<p id="L601"><br></p>
<p id="L602">「うん。とはいえ、俺も最近になるまで家に引きこもってたからな。</p>
<p id="L603">　さて、どんな遊びをしていいのか」</p>
<p id="L604"><br></p>
<p id="L605">　シルフはもじもじと手を合わせて、上目遣いにこっちを見てくる。</p>
<p id="L606">　背丈は同じぐらいなのだが、背中をまるめているので、俺を見上げてしまうのだ。</p>
<p id="L607"><br></p>
<p id="L608">「ねえ、なんで、ぼく、とか、おれ、とか言い方を変えるの？」</p>
<p id="L609">「え？　ああ。相手によって変えないと失礼になるからな。</p>
<p id="L610">　目上の相手には敬語だよ」</p>
<p id="L611">「けいご？」</p>
<p id="L612">「さっき、俺が使ってたような言葉のこと」</p>
<p id="L613">「ふぅん？」</p>
<p id="L614"><br></p>
<p id="L615">　よくわからなかったらしい。</p>
<p id="L616">　誰でもおいおいわかっていくことさ。</p>
<p id="L617">　それが大人になるってことだよ。</p>
<p id="L618"><br></p>
<p id="L619">「それより、さっきの、あれ。教えて」</p>
<p id="L620">「さっきのあれ？」</p>
<p id="L621"><br></p>
<p id="L622">　シルフは目をキラキラさせながら、身振り手振りで説明してくれる。</p>
<p id="L623"><br></p>
<p id="L624">「手から、あったかいお水がざばーって出るのと、</p>
<p id="L625">　暖かい風が、ぶわーって出るの」</p>
<p id="L626">「あー。あれね」</p>
<p id="L627"><br></p>
<p id="L628">　泥を洗い流した時に使った魔術のことだ。</p>
<p id="L629"><br></p>
<p id="L630">「ボクにも、出来る？」</p>
<p id="L631">「難しいけど、練習すれば誰にでも出来るよ……多分ね」</p>
<p id="L632"><br></p>
<p id="L633">　最近は魔力量が上がりすぎてどれぐらい魔力を消費してるのかわからないし、</p>
<p id="L634">　そもそもこっちの人らの魔力量が基本的にどれぐらいあるのかわからない。</p>
<p id="L635">　とはいえ、水を火で温めているだけ。</p>
<p id="L636">　無詠唱でいきなりお湯、とまではいかないだろうが、</p>
<p id="L637">　混合魔術として使えば、誰にでも再現できる。</p>
<p id="L638">　だから多分大丈夫だ。多分。</p>
<p id="L639"><br></p>
<p id="L640">「ようし。じゃあ今日から特訓だ！」</p>
<p id="L641"><br></p>
<p id="L642">　こんな感じで、俺はシルフと日が暮れるまで遊んだ。</p>
<p id="L643"><br></p>
<p id="L644"><br></p>
<p id="L645">---</p>
<p id="L646"><br></p>
<p id="L647"><br></p>
<p id="L648">　家に帰ると、パウロが怒っていた。</p>
<p id="L649">　怒っていますという感じに腰に手をやって、玄関の前で仁王立ちしていた。</p>
<p id="L650"><br></p>
<p id="L651">　さて、何をやらかしたっけか。</p>
<p id="L652">　心当たりといえば、大切に保管してある<ruby>御神体<rp>(</rp><rt>パンツ</rt><rp>)</rp></ruby>を発見された事ぐらいだが……。</p>
<p id="L653"><br></p>
<p id="L654">「父様。只今帰りました」</p>
<p id="L655">「なんで怒っているかわかっているか？」</p>
<p id="L656">「わかりません」</p>
<p id="L657"><br></p>
<p id="L658">　まずはシラを切る。</p>
<p id="L659">　もしパン……御神体を発見されていなかった場合、やぶ蛇になるからな。</p>
<p id="L660"><br></p>
<p id="L661">「さっき、エトの所の奥さんがきてな、お前、エトの所のソマル坊を殴ったそうじゃないか」</p>
<p id="L662"><br></p>
<p id="L663">　エト、ソマル。</p>
<p id="L664">　誰だそいつ？</p>
<p id="L665"><br></p>
<p id="L666">　聞き覚えのない名前が出てきて、俺は考える。</p>
<p id="L667">　基本的に、俺は村では挨拶ぐらいしかしていない。</p>
<p id="L668">　名前を言えば、向こうも名乗ってくれるが、</p>
<p id="L669">　その中にさて、エトという名前がいたような、いなかったような……。</p>
<p id="L670">　ん、まてよ。</p>
<p id="L671"><br></p>
<p id="L672">「今日の話ですか？」</p>
<p id="L673">「そうだ」</p>
<p id="L674"><br></p>
<p id="L675">　今日出会ったのは、シルフとロールズと、三人のクソガキだけだ。</p>
<p id="L676">　てことは、ソマルってのは三人のクソガキの一人か。</p>
<p id="L677"><br></p>
<p id="L678">「殴ってはいません。泥を投げつけただけです」</p>
<p id="L679">「この間、父さんが言ったことを覚えているか？」</p>
<p id="L680">「男の強さは威張るためにあるんじゃない？」</p>
<p id="L681">「そうだ」</p>
<p id="L682"><br></p>
<p id="L683">　ははーん。</p>
<p id="L684">　なるほど、そういえば、さり際に魔族と仲良くしてるのを言いふらしてやるとか言ってたな。</p>
<p id="L685">　あいつだな。</p>
<p id="L686">　どういう嘘をついて殴った事になったかわからないが、とりあえず俺のネガキャンをしたという所か。</p>
<p id="L687"><br></p>
<p id="L688">「父様がどういう話を聞いたのかはわかりませんが……」</p>
<p id="L689">「違う！　悪いことをしたら、まずはごめんなさいだ！」</p>
<p id="L690"><br></p>
<p id="L691">　ぴしゃりと言われた。</p>
<p id="L692">　どういう話を聞いたのかはわからないが、鵜呑みにしているらしい。</p>
<p id="L693">　参ったな。</p>
<p id="L694">　こういう状況だと、シルフがイジメられている所を助けたと言っても、ウソくさい。</p>
<p id="L695">　とはいえ、一から説明するしかないか。</p>
<p id="L696"><br></p>
<p id="L697">「実は道を歩いていたら……」</p>
<p id="L698">「言い訳をするな！」</p>
<p id="L699"><br></p>
<p id="L700">　段々イライラしてきた。</p>
<p id="L701">　ウソ以前に、俺の言い分を聞いてくれる気すらないようだ。</p>
<p id="L702">　とりあえずごめんなさいしてしまってもいいのだが、それはパウロのためにもよくない気がする。</p>
<p id="L703"><br></p>
<p id="L704">　いずれ作られるであろう弟か妹に理不尽な思いをして欲しくはない。</p>
<p id="L705">　この叱り方は、ダメだ。</p>
<p id="L706"><br></p>
<p id="L707">「………」</p>
<p id="L708">「どうした、何故なにも言わない？」</p>
<p id="L709">「口を開けば言い訳をするなと怒鳴られるからです」</p>
<p id="L710">「なに！？」</p>
<p id="L711"><br></p>
<p id="L712">　パウロの眦が釣り上がる。</p>
<p id="L713"><br></p>
<p id="L714">「子供が何か言う前に怒鳴りつけて謝らせる。</p>
<p id="L715">　大人のやることは手っ取り早くて簡単で、羨ましいですね」</p>
<p id="L716">「ルディ！」</p>
<p id="L717"><br></p>
<p id="L718">　バシッ、と頬に熱い衝撃。</p>
<p id="L719">　殴られた。</p>
<p id="L720">　が、予測していた。</p>
<p id="L721">　挑発をしたら殴られる、当然だ。</p>
<p id="L722">　だからぐっと踏みとどまった。</p>
<p id="L723"><br></p>
<p id="L724">　殴られるのなんて二十年ぶりぐらいか………。</p>
<p id="L725">　いや、家を出る時にぼっこぼこにされたから、五年ぶりか。</p>
<p id="L726"><br></p>
<p id="L727">「父様。僕は今まで、出来る限り良い子でいるように努力してきました。父様や母様の言いつけに背いたことは一度もありませんし、やれと言われた事も全力で取り組んできたつもりです」</p>
<p id="L728">「そ、それは関係ないだろう」</p>
<p id="L729"><br></p>
<p id="L730">　パウロも殴るつもりはなかったらしい。</p>
<p id="L731">　目に見えて狼狽していた。</p>
<p id="L732">　まあいい。好都合だ。</p>
<p id="L733"><br></p>
<p id="L734">「いいえ、あります。僕は父様を安心させるように、信頼してもらえるようにと頑張ってきたんです。父様はそんな僕の言い分は一切聞かず、僕が知らない相手からの言葉を鵜呑みにして怒鳴りつけ、あまつさえ手まで上げたんです」</p>
<p id="L735">「しかし、ソマル坊は確かに怪我をして……」</p>
<p id="L736"><br></p>
<p id="L737">　怪我？</p>
<p id="L738">　それは知らないな。</p>
<p id="L739">　自分で付けたのか？</p>
<p id="L740">　当たり屋みたいなやつだな……。</p>
<p id="L741"><br></p>
<p id="L742">　だが残念だったな。</p>
<p id="L743">　俺には大義名分がある。</p>
<p id="L744">　怪我なんていうちんけな嘘じゃなくてな。</p>
<p id="L745"><br></p>
<p id="L746">「仮にその怪我が僕のせいだったとしても、僕が謝ることはありません。僕は父様の言いつけには背いていませんし、胸を張って僕がやったと言いましょう」</p>
<p id="L747">「………ちょっとまて、何があったんだ？」</p>
<p id="L748"><br></p>
<p id="L749">　おっと、気になってきたな？</p>
<p id="L750">　でも、聞かないと決めたのはお前だぜ。</p>
<p id="L751"><br></p>
<p id="L752">「言い訳は聞きたくないのでは？」</p>
<p id="L753"><br></p>
<p id="L754">　そう言うと、パウロはグッと苦い顔をした。</p>
<p id="L755">　もうひと息か。</p>
<p id="L756"><br></p>
<p id="L757">「安心してください父様。</p>
<p id="L758">　次回からは三人掛かりで無抵抗の相手一人を攻撃しているのを見ても無視します。</p>
<p id="L759">　あまつさえ四対一になるように僕の方から動きましょう。</p>
<p id="L760">　弱い者を寄ってたかってイジメる事こそがグレイラット家の誇りであり家訓なのだと周囲に喧伝しましょう。</p>
<p id="L761">　そして大きくなったら家を出て、二度とグレイラットとは名乗らないことにします。</p>
<p id="L762">　実際の暴力は無視して、言葉の暴力を許すような、そんなゴミクズの家の人間だと名乗るのは恥ずかしいので」</p>
<p id="L763"><br></p>
<p id="L764">　パウロは絶句していた。</p>
<p id="L765">　顔を赤くし、青くし、葛藤がかいま見える。</p>
<p id="L766">　怒るかな？</p>
<p id="L767">　もう一息必要かな？</p>
<p id="L768">　やめておいた方がいいぞパウロよ。</p>
<p id="L769">　俺はこれでも、２０年以上勝てるわけのない口論で言い逃れ続けてきた男。</p>
<p id="L770">　たった一つでも切り口があれば、最低でも引き分けにもっていけるのだ。</p>
<p id="L771">　まして今回は完全なる正義。</p>
<p id="L772">　お前に勝ち目はない。</p>
<p id="L773"><br></p>
<p id="L774">「……………すまなかった。父さんが悪かった。話してくれ」</p>
<p id="L775"><br></p>
<p id="L776">　パウロが頭を下げた。</p>
<p id="L777">　そうだな。変な意地を張ってもお互い不幸になるだけだ。</p>
<p id="L778">　悪ければ謝る。それが一番だよ。</p>
<p id="L779"><br></p>
<p id="L780">　俺も溜飲を下げ、事の詳細を出来る限り客観的に話した。</p>
<p id="L781"><br></p>
<p id="L782">　丘の上に登ろうとしていると声が聞こえた。</p>
<p id="L783">　三人の子供が休畑の中から、道を歩く一人の子供に泥を投げつけていた。</p>
<p id="L784">　泥を１～２発投げつけてから説き伏せると、彼らは悪態をついてどこかへ行ってしまった。</p>
<p id="L785">　泥を投げつけられていた子を魔術で洗ってやり、一緒に遊んだ。</p>
<p id="L786"><br></p>
<p id="L787">　といった感じに。</p>
<p id="L788"><br></p>
<p id="L789">「ですので、謝るのでしたら、そのソマル君とやらがシルフに謝るのが先です。</p>
<p id="L790">　体の傷はすぐ消えますが、心の傷はすぐには消えませんので」</p>
<p id="L791">「………そうだな、父さんの勘違いだった。すまん」</p>
<p id="L792"><br></p>
<p id="L793">　パウロはしょんぼりと肩を落としていた。</p>
<p id="L794">　それを見て、俺は昼間にロールズから聞いた話を思い出す。</p>
<p id="L795"><br></p>
<p id="L796">『君と話していると親としての自信を失うらしい』</p>
<p id="L797"><br></p>
<p id="L798">　もしかすると、</p>
<p id="L799">　パウロは叱ることで父親らしい部分を見せたかったのかもしれない。</p>
<p id="L800">　まぁ、今回は失敗したようだが。</p>
<p id="L801"><br></p>
<p id="L802">「謝る必要はありません。今後も僕が間違っていると思ったら、容赦なく叱って下さい。</p>
<p id="L803">　ただ、言い分も聞いてくれると助かります。言葉足らずだったり、言い訳にしか聞こえなかったりする時もありますが、言いたいことはありますので、意を汲んでいただければとおもいます」</p>
<p id="L804">「ああ、気をつけるよ。もっとも、お前は間違ったりしなさそうだが……」</p>
<p id="L805">「でしたら、そのうち出来る僕の弟か妹を叱る時の教訓にしてください」</p>
<p id="L806">「………そうするよ」</p>
<p id="L807"><br></p>
<p id="L808">　自嘲げにそう言った。</p>
<p id="L809">　言い過ぎただろうか。</p>
<p id="L810"><br></p>
<p id="L811">　五歳の息子に言い負ける。</p>
<p id="L812">　うん。俺だったら凹む。</p>
<p id="L813">　パウロはハッキリと落ち込んだ様子で、見ていて気の毒になっている。</p>
<p id="L814">　父親としてはまだ若いもんなコイツ。</p>
<p id="L815"><br></p>
<p id="L816">「そういえば、父様は、いま何歳でしたっけ？」</p>
<p id="L817">「ん？　２４だが？」</p>
<p id="L818">「そうですか」</p>
<p id="L819"><br></p>
<p id="L820">　１９で結婚して俺を作ったのか。</p>
<p id="L821">　この世界の平均結婚年齢が何歳ぐらいかはわからないが、現代日本のように３０歳前後という事もないだろう。</p>
<p id="L822">　魔物とか戦争とかも日常的に起こっているようだし、結婚年齢としては妥当な線なのか。</p>
<p id="L823">　一回りも下の年齢の男が結婚して子供を産んで子育てで悩んでいる。</p>
<p id="L824">　それだけで、３４歳住所不定無職職歴無しだった俺に勝てる部分は無いと思うのだが……。</p>
<p id="L825"><br></p>
<p id="L826">　まぁ、いっか。</p>
<p id="L827"><br></p>
<p id="L828">「父様、今度シルフを家に連れてきてもいいですか？」</p>
<p id="L829">「え？　ああ、もちろんだ」</p>
<p id="L830"><br></p>
<p id="L831">　俺はその返答に満足すると、父親と一緒に家の中へと入っていった。</p>
<p id="L832">　パウロが魔族に偏見を持っていなくてよかったと思う。</p>
<p id="L833"><br></p>
<p id="L834"><br></p>
<p id="L835"><br></p>
<p id="L836"><br></p>
<p id="L837">--- パウロ視点 ---</p>
<p id="L838"><br></p>
<p id="L839"><br></p>
<p id="L840">　息子が怒っていた。</p>
<p id="L841">　今まで、さして感情らしい感情を見せてこなかった息子が、静かに激怒していた。</p>
<p id="L842">　どうしてこうなったのだろうか。</p>
<p id="L843"><br></p>
<p id="L844">　事の起こりは昼下がり、凄い剣幕でエトの奥方が屋敷に怒鳴りこんできた。</p>
<p id="L845">　近所で悪ガキとして評判の子供ソマルを連れており、ソマルの目尻には青い痣ができていた。</p>
<p id="L846">　剣士としてそれなりに修羅場をくぐってきたオレには、それが殴られてついたものだとすぐに分かった。</p>
<p id="L847">　奥方の話は要領を得なかったが、要約するに、うちの息子がソマル坊を殴ったらしい。</p>
<p id="L848"><br></p>
<p id="L849">　それを聞いて、オレは内心でほっとした。</p>
<p id="L850"><br></p>
<p id="L851">　大方、外で遊んでいたら、ソマルたちが遊んでいる所を見かけて、仲間に入れてもらおうとしたのだろう。</p>
<p id="L852">　しかし、息子は他の子供たちと違う。</p>
<p id="L853">　あの歳で水聖級魔術師だ。</p>
<p id="L854">　きっと偉そうに何かを言ったのだろう。</p>
<p id="L855">　そして反発を受け、喧嘩になったのだ。　</p>
<p id="L856">　息子はなんだかやけに聡くて大人びているが、子供らしい所もあるのだ。</p>
<p id="L857"><br></p>
<p id="L858">　エトの奥方は顔を赤くしたり青くしたりしながら大事にしようとしているが、所詮は子供の喧嘩だ。</p>
<p id="L859">　見たところ、怪我の方も痕になったりはしないだろう。</p>
<p id="L860">　オレが叱って終わりだ。</p>
<p id="L861"><br></p>
<p id="L862">　子供なら殴り合いの喧嘩の一つもするだろう。</p>
<p id="L863">　しかし、ルーデウスは他の子供より力を持っている。</p>
<p id="L864">　若くして水聖級の魔術師となったロキシーの弟子であり、</p>
<p id="L865">　三歳の頃からオレの指導で訓練してきた身体だ。</p>
<p id="L866">　きっと喧嘩も一方的になったはずだ。</p>
<p id="L867">　今回は大丈夫だったようだが、頭に血がのぼってカッとなれば、やりすぎてしまうかもしれない。</p>
<p id="L868"><br></p>
<p id="L869">　これはキツめに叱らなければならない。</p>
<p id="L870">　頭のいいルーデウスになら、ソマル坊を殴らずに済ませる方法はあったはずなのだ。</p>
<p id="L871">　殴るというのは短絡的で、もっと考えなければならない行動だと教える必要があった。</p>
<p id="L872"><br></p>
<p id="L873"><br></p>
<p id="L874">　それなのに、どうしてこうなった……。</p>
<p id="L875"><br></p>
<p id="L876">　息子は全然謝るつもりはないらしい。</p>
<p id="L877">　それどころか、虫を見るような目でオレを見てくる。</p>
<p id="L878">　確かに、息子にしてみれば、対等な立場で喧嘩をしたつもりなのかもしれないが、しかし力の強い者はその強さを自覚しなければならない。</p>
<p id="L879">　まして、怪我をさせたのだ。</p>
<p id="L880">　とにかく、とにかく謝らせよう。</p>
<p id="L881">　賢い息子のことだ。今は納得できないかもしれないが、必ず自分で答えにたどり着いてくれるだろう。</p>
<p id="L882">　そう思い、強い口調で言い聞かせようとしたら、皮肉げに嫌味を言われた。</p>
<p id="L883"><br></p>
<p id="L884">　ついカッとなって殴ってしまった。</p>
<p id="L885"><br></p>
<p id="L886">　力の強い者はその力を自覚して、</p>
<p id="L887">　自分より弱い者に軽々しく暴力を振るうな、と説教しようとしていたのに。</p>
<p id="L888">　オレは殴ってしまったのだ。</p>
<p id="L889"><br></p>
<p id="L890">　今のは自分が悪かった。</p>
<p id="L891">　そう思ったが、説教をしている立場で口にするわけにもいかない。</p>
<p id="L892">　しかし、今しがた自分のした行動をするなと言っても説得力がない。</p>
<p id="L893">　しどろもどろになっているうちに、息子は遠まわしに自分は悪いことをしていないと言い出し、それがダメなら家を出るとまで言い出した。</p>
<p id="L894">　売り言葉に買い言葉で、出て行けと言いそうになったが、ぐっと我慢する。</p>
<p id="L895">　我慢しなければならない所だった。</p>
<p id="L896"><br></p>
<p id="L897">　そもそも、だ。</p>
<p id="L898">　オレ自身も、堅苦しい家で厳格な父が頭ごなしに叱ってくるのに嫌気がさし、大喧嘩の末に家を飛び出したのだ。</p>
<p id="L899">　オレは、父の血を継いでいる。</p>
<p id="L900">　頑固で融通のきかない父の血を、継いでいる。</p>
<p id="L901">　そしてルーデウスもだ。</p>
<p id="L902">　この頑固な所を見ろ。</p>
<p id="L903">　ルーデウスも自分の子供だ。</p>
<p id="L904">　オレはあの日、今すぐ出て行けと言われ、売り言葉に買い言葉で家を出ていった。</p>
<p id="L905">　ルーデウスは出ていくだろう。</p>
<p id="L906">　大人になったら出ていくと言っていたが、いますぐ出て行けと言われれば、すぐに出ていくだろう。</p>
<p id="L907"><br></p>
<p id="L908">　父はオレが旅にでてしばらくして病に倒れ、死んだと聞く。</p>
<p id="L909">　風の噂では、今際の際まであの日の喧嘩のことを後悔していたらしい。</p>
<p id="L910">　だから、オレにだって負い目はある。</p>
<p id="L911">　いや、ハッキリ言おう、後悔している。</p>
<p id="L912">　それに照らしあわせて考えるに、ここでルーデウスに出て行けと言って本当に出ていかれたら、間違いなく後悔するだろう。</p>
<p id="L913">　オレはもちろん、ルーデウスも後悔する。</p>
<p id="L914">　我慢だ。</p>
<p id="L915">　経験から学んだじゃないか。</p>
<p id="L916">　それに、子供が生まれた時に決めたじゃないか。</p>
<p id="L917">　あの父のようにはならないと。</p>
<p id="L918"><br></p>
<p id="L919">「………………すまなかった。父さんが悪かった。話してくれ」</p>
<p id="L920"><br></p>
<p id="L921">　謝罪は自然と口に出た。</p>
<p id="L922">　すると、ルーデウスはスッと表情を和らげ、淡々と説明してくれた。</p>
<p id="L923">　なんでも、ロールズの子がイジメられていた所に通りがかって、助けに入ったのだという。</p>
<p id="L924">　殴るどころか、泥玉を投げ合っただけで、喧嘩すらしていないという。</p>
<p id="L925"><br></p>
<p id="L926">　その話が本当なら、ルーデウスは胸を張って誇れる事をしている。</p>
<p id="L927">　だというのに、褒められるどころか言い分も聞いてもらえずに殴られた事になる。</p>
<p id="L928">　ああ、思い出す。</p>
<p id="L929">　自分が幼い頃にも、そういう事は何度もあった。</p>
<p id="L930">　父は一切聞いてくれず、オレの至らない部分ばかりを責めた。</p>
<p id="L931">　その度にやるせない気持ちになったものだ。　</p>
<p id="L932"><br></p>
<p id="L933">　失敗した。</p>
<p id="L934">　何が説教しなければ、だ。</p>
<p id="L935"><br></p>
<p id="L936">　はぁ……。</p>
<p id="L937"><br></p>
<p id="L938">　ルーデウスは、そんな自分を責めることなく、最後には慰めてすらくれた。</p>
<p id="L939">　できた息子だ。できすぎだ。</p>
<p id="L940">　本当に自分の息子なのだろうか……。</p>
<p id="L941">　いや、ゼニスが浮気しそうな相手の中に、あんな優秀な子供の父親はいない。</p>
<p id="L942"><br></p>
<p id="L943">　うう、自分の種がこんなに優秀だったとは……。</p>
<p id="L944">　誇らしいと思うより、胃が痛い。</p>
<p id="L945"><br></p>
<p id="L946">「父様、今度シルフを家に連れてきてもいいですか？」</p>
<p id="L947">「え？　ああ、もちろんだ」</p>
<p id="L948"><br></p>
<p id="L949">　しかし、今は息子に初の友達ができたことを喜んでおこう。</p>
</div>
</div>